defusedcsv/__init__.py
defusedcsv/csv.py
defusedcsv-1.1.0.dist-info/AUTHORS
defusedcsv-1.1.0.dist-info/LICENSE
defusedcsv-1.1.0.dist-info/METADATA
defusedcsv-1.1.0.dist-info/WHEEL
defusedcsv-1.1.0.dist-info/top_level.txt
defusedcsv-1.1.0.dist-info/RECORD
