Metadata-Version: 2.1
Name: defusedcsv
Version: 1.1.0
Summary: Drop-in replacement for Python's CSV library that tries to mitigate CSV injection attacks
Home-page: https://github.com/raphaelm/defusedcsv
Author: Raphael Michel
Author-email: mail@raphaelmichel.de
License: Apache License 2.0
Keywords: csv injection defuse save
Platform: UNKNOWN
Classifier: Intended Audience :: Developers
Classifier: Intended Audience :: Other Audience
Classifier: License :: OSI Approved :: Apache Software License
Classifier: Programming Language :: Python :: 3.4
Classifier: Programming Language :: Python :: 3.5
Classifier: Programming Language :: Python :: 3.6
